CHANGES
LICENSE
MANIFEST.in
README
example_script.py
setup.py
test.py
django_standalone.egg-info/PKG-INFO
django_standalone.egg-info/SOURCES.txt
django_standalone.egg-info/dependency_links.txt
django_standalone.egg-info/requires.txt
django_standalone.egg-info/top_level.txt
standalone/__init__.py
standalone/conf.py
standalone/models.py
standalone/tests.py