Metadata-Version: 1.0
Name: django-standalone
Version: 0.3
Summary: use the Django ORM with standalone scripts
Home-page: http://bitbucket.org/rfc1437/django-standalone/
Author: Georg Bauer
Author-email: gb@rfc1437.de
License: BSD
Keywords: django standalone script orm
Platform: UNKNOWN
Classifier: Development Status :: 4 - Beta
Classifier: Framework :: Django
Classifier: Intended Audience :: Developers
Classifier: License :: OSI Approved :: BSD License
Classifier: Operating System :: OS Independent
Classifier: Programming Language :: Python
Classifier: Topic :: Utilities
